{
  "slug": "elias-motsoaledi",
  "title": "Elias Motsoaledi",
  "lore": "He walked in from a set that stopped printing, staff worn smooth by the highway. Whatever pack he joins gains a little dust and a little grace.",
  "omen": "Walking since the first edition.",
  "rarity": "uncommon",
  "atk": 7,
  "def": 7,
  "trigger": "RUG WIND",
  "generatedBy": "named for people in the writings of HST · Ram Dass · McKenna · Jordan · Watts · Mandela",
  "provenance": {
    "minted": null,
    "mintPrice": null,
    "lastSale": null,
    "floor": null,
    "battlesWon": 0,
    "battlesLost": 0,
    "timesWagered": 0,
    "burnsSurvived": 0,
    "owners": []
  }
}