{
  "slug": "greenback",
  "title": "Greenback",
  "lore": "Engraved like legal tender and exactly as trustworthy. Fold him twice and he appreciates.",
  "omen": "In nothing we trust. Print anyway.",
  "rarity": "rare",
  "atk": 4,
  "def": 4,
  "trigger": "BLOCK OMEN",
  "generatedBy": "vision-named (art-read, curated)",
  "provenance": {
    "minted": null,
    "mintPrice": null,
    "lastSale": null,
    "floor": null,
    "battlesWon": 0,
    "battlesLost": 0,
    "timesWagered": 0,
    "burnsSurvived": 0,
    "owners": []
  }
}