{
  "slug": "red-cackle",
  "title": "Red Cackle",
  "lore": "Mid-laugh in a red suit with smoke for punctuation. The joke is the market. The market never gets it.",
  "omen": "HA — and the candle turns.",
  "rarity": "uncommon",
  "atk": 3,
  "def": 6,
  "trigger": "DEEP WATER",
  "generatedBy": "vision-named (art-read, curated)",
  "provenance": {
    "minted": null,
    "mintPrice": null,
    "lastSale": null,
    "floor": null,
    "battlesWon": 0,
    "battlesLost": 0,
    "timesWagered": 0,
    "burnsSurvived": 0,
    "owners": []
  }
}