{
  "slug": "rinzai",
  "title": "Rinzai",
  "lore": "He hoards the dead hours between weekends under his pillow like contraband. Wake him and the next season starts early and mean.",
  "omen": "Five more blocks. Please.",
  "rarity": "common",
  "atk": 9,
  "def": 3,
  "trigger": "MOON CANDLE",
  "generatedBy": "named for people in the writings of HST · Ram Dass · McKenna · Jordan · Watts · Mandela",
  "provenance": {
    "minted": null,
    "mintPrice": null,
    "lastSale": null,
    "floor": null,
    "battlesWon": 0,
    "battlesLost": 0,
    "timesWagered": 0,
    "burnsSurvived": 0,
    "owners": []
  }
}