{
 "slug": "silver-press",
 "title": "Grayscale Gate-Crashers",
 "lore": "Struck in silver foil with a cartoon witness in the margin. The press only ran once before they seized it.",
 "omen": "One pressing. No reprints.",
 "rarity": "common",
 "atk": 4,
 "def": 4,
 "trigger": "STILL AIR",
 "generatedBy": "vision-named (art-read, curated)",
 "provenance": {
  "minted": null,
  "mintPrice": null,
  "lastSale": null,
  "floor": null,
  "battlesWon": 0,
  "battlesLost": 0,
  "timesWagered": 0,
  "burnsSurvived": 0,
  "owners": []
 },
 "traits": {
  "archetype": "human-portrait",
  "subjects": "duo",
  "tags": [
   "framed",
   "human-portrait",
   "duo"
  ],
  "rarityScore": -7.541,
  "visual": {
   "sparkle": 0.009,
   "gold": 0,
   "colorfulness": 20.5,
   "paletteDiv": 0,
   "neon": 0,
   "bgVar": 123,
   "contrast": 0.18
  },
  "derivedBy": "trait-based (pixel traits + vision archetype)"
 },
 "factoid": "Nobody remembers inviting the cartoons. The disco balls, however, RSVP'd months ago."
}