{
  "slug": "white-robe",
  "title": "White Robe",
  "lore": "Dressed all in white like a man with nothing left to confess, which is its own kind of lie. The dog knows. The dog always knows.",
  "omen": "Clean robe, filthy ledger.",
  "rarity": "common",
  "atk": 7,
  "def": 7,
  "trigger": "BURN WAVE",
  "generatedBy": "vision-named (art-read, curated psychedelic 1-2 word)",
  "provenance": {
    "minted": null,
    "mintPrice": null,
    "lastSale": null,
    "floor": null,
    "battlesWon": 0,
    "battlesLost": 0,
    "timesWagered": 0,
    "burnsSurvived": 0,
    "owners": []
  },
  "traits": {
    "archetype": "frog-pepe",
    "subjects": "group",
    "tags": [
      "framed",
      "frog-pepe",
      "group"
    ],
    "rarityScore": -3.661,
    "visual": {
      "sparkle": 0.029,
      "gold": 0,
      "colorfulness": 53.4,
      "paletteDiv": 4,
      "neon": 0.022,
      "bgVar": 98.4,
      "contrast": 0.258
    },
    "derivedBy": "trait-based (pixel traits + vision archetype)"
  },
  "factoid": "The word 'robe' shares a Germanic root with 'rob,' since fine garments were once prized plunder taken from enemies."
}